scm_python_design_pattern/__init__.py
scm_python_design_pattern/lib/__init__.py
scm_python_design_pattern/lib/design_pattern.py
scm_python_design_pattern/lib/main.py
scm_python_design_pattern/tapps/code/designPattern.py
scm_python_design_pattern-1.1.0.dist-info/METADATA
scm_python_design_pattern-1.1.0.dist-info/WHEEL
scm_python_design_pattern-1.1.0.dist-info/top_level.txt
scm_python_design_pattern-1.1.0.dist-info/RECORD
